USRVoiceModem/__init__.py
USRVoiceModem/callAndAnswer.py
USRVoiceModem/speechToText.py
USRVoiceModem-1.0.0.dist-info/LICENSE
USRVoiceModem-1.0.0.dist-info/METADATA
USRVoiceModem-1.0.0.dist-info/WHEEL
USRVoiceModem-1.0.0.dist-info/entry_points.txt
USRVoiceModem-1.0.0.dist-info/top_level.txt
USRVoiceModem-1.0.0.dist-info/RECORD
